pddl/__init__.py
pddl/__main__.py
pddl/__version__.py
pddl/_validation.py
pddl/action.py
pddl/core.py
pddl/custom_types.py
pddl/exceptions.py
pddl/formatter.py
pddl/requirements.py
pddl/helpers/__init__.py
pddl/helpers/base.py
pddl/helpers/cache_hash.py
pddl/logic/__init__.py
pddl/logic/base.py
pddl/logic/effects.py
pddl/logic/functions.py
pddl/logic/helpers.py
pddl/logic/predicates.py
pddl/logic/terms.py
pddl/parser/__init__.py
pddl/parser/_update_type_tags.py
pddl/parser/base.py
pddl/parser/domain.py
pddl/parser/grammar.lark
pddl/parser/plan.py
pddl/parser/problem.py
pddl/parser/symbols.py
pddl/parser/typed_list_parser.py
pddl-0.4.5.data/data/pddl/parser/grammar.lark
pddl-0.4.5.dist-info/licenses/LICENSE
pddl-0.4.5.dist-info/METADATA
pddl-0.4.5.dist-info/WHEEL
pddl-0.4.5.dist-info/entry_points.txt
pddl-0.4.5.dist-info/top_level.txt
pddl-0.4.5.dist-info/RECORD
