Metadata-Version: 2.4
Name: pddl
Version: 0.4.5
Summary: PDDL parser
Home-page: https://github.com/AI-Planning/pddl.git
Author: Marco Favorito, Francesco Fuggitti, Christian Muise
Author-email: marco.favorito@gmail.com, francesco.fuggitti@gmail.com, christian.muise@queensu.ca
License: MIT License
Keywords: pddl
Classifier: Development Status :: 2 - Pre-Alpha
Classifier: Intended Audience :: Education
Classifier: License :: OSI Approved :: MIT License
Classifier: Natural Language :: English
Classifier: Programming Language :: Python :: 3
Classifier: Programming Language :: Python :: 3.9
Classifier: Programming Language :: Python :: 3.10
Classifier: Programming Language :: Python :: 3.11
Classifier: Programming Language :: Python :: 3.12
Requires-Python: >=3.9
License-File: LICENSE
Requires-Dist: lark<1.2.0,>=1.1.5
Requires-Dist: click<9.0.0,>=8.1.3
Dynamic: author
Dynamic: author-email
Dynamic: classifier
Dynamic: description
Dynamic: description-content-type
Dynamic: home-page
Dynamic: keywords
Dynamic: license
Dynamic: license-file
Dynamic: requires-dist
Dynamic: requires-python
Dynamic: summary
